LICENSE.txt
MANIFEST.in
README.txt
setup.py
lfc_contact_form/__init__.py
lfc_contact_form/forms.py
lfc_contact_form/models.py
lfc_contact_form.egg-info/PKG-INFO
lfc_contact_form.egg-info/SOURCES.txt
lfc_contact_form.egg-info/dependency_links.txt
lfc_contact_form.egg-info/not-zip-safe
lfc_contact_form.egg-info/requires.txt
lfc_contact_form.egg-info/top_level.txt
lfc_contact_form/locale/de/LC_MESSAGES/django.mo
lfc_contact_form/locale/de/LC_MESSAGES/django.po